trieve_py_client/__init__.py
trieve_py_client/api_client.py
trieve_py_client/api_response.py
trieve_py_client/configuration.py
trieve_py_client/exceptions.py
trieve_py_client/py.typed
trieve_py_client/rest.py
trieve_py_client/api/__init__.py
trieve_py_client/api/analytics_api.py
trieve_py_client/api/auth_api.py
trieve_py_client/api/chunk_api.py
trieve_py_client/api/chunk_group_api.py
trieve_py_client/api/dataset_api.py
trieve_py_client/api/events_api.py
trieve_py_client/api/file_api.py
trieve_py_client/api/health_api.py
trieve_py_client/api/invitation_api.py
trieve_py_client/api/message_api.py
trieve_py_client/api/metrics_api.py
trieve_py_client/api/organization_api.py
trieve_py_client/api/public_api.py
trieve_py_client/api/stripe_api.py
trieve_py_client/api/topic_api.py
trieve_py_client/api/user_api.py
trieve_py_client/models/__init__.py
trieve_py_client/models/add_chunk_to_group_req_payload.py
trieve_py_client/models/add_to_cart.py
trieve_py_client/models/api_key_request_params.py
trieve_py_client/models/api_key_resp_body.py
trieve_py_client/models/api_version.py
trieve_py_client/models/audio.py
trieve_py_client/models/auth_query.py
trieve_py_client/models/autocomplete_req_payload.py
trieve_py_client/models/batch_queued_chunk_response.py
trieve_py_client/models/bulk_delete_chunk_payload.py
trieve_py_client/models/button_trigger.py
trieve_py_client/models/chat_message_proxy.py
trieve_py_client/models/chunk_filter.py
trieve_py_client/models/chunk_group.py
trieve_py_client/models/chunk_group_and_file_id.py
trieve_py_client/models/chunk_html_content_req_payload.py
trieve_py_client/models/chunk_metadata.py
trieve_py_client/models/chunk_metadata_string_tag_set.py
trieve_py_client/models/chunk_metadata_types.py
trieve_py_client/models/chunk_metadata_with_position.py
trieve_py_client/models/chunk_metadata_with_score.py
trieve_py_client/models/chunk_req_payload.py
trieve_py_client/models/chunk_req_payload_fields.py
trieve_py_client/models/chunk_req_payload_mapping.py
trieve_py_client-0.12.11.dist-info/METADATA
trieve_py_client-0.12.11.dist-info/WHEEL
trieve_py_client-0.12.11.dist-info/top_level.txt
trieve_py_client-0.12.11.dist-info/RECORD
