Metadata-Version: 2.2
Name: trieve_py_client
Version: 0.12.11
Summary: Trieve API
Home-page: https://trieve.ai
Author: Trieve Team
Author-email: developers@trieve.ai
License: BSL
Keywords: OpenAPI,OpenAPI-Generator,Trieve API
Requires-Dist: urllib3<=2.3.0,>=1.25.3
Requires-Dist: python-dateutil
Requires-Dist: pydantic>=2
Requires-Dist: typing-extensions>=4.7.1
Dynamic: author
Dynamic: author-email
Dynamic: description
Dynamic: description-content-type
Dynamic: home-page
Dynamic: keywords
Dynamic: license
Dynamic: requires-dist
Dynamic: summary
